README.md
setup.py
StarkLego/__init__.py
StarkLego.egg-info/PKG-INFO
StarkLego.egg-info/SOURCES.txt
StarkLego.egg-info/dependency_links.txt
StarkLego.egg-info/requires.txt
StarkLego.egg-info/top_level.txt
StarkLego/environments/__init__.py
StarkLego/environments/env_low_height.py
StarkLego/lego_builders/__init__.py
StarkLego/lego_builders/model/__init__.py
StarkLego/lego_builders/model/blocks.py
StarkLego/lego_builders/model/dimensions.py
StarkLego/lego_builders/model/specifications.py
StarkLego/lego_builders/service/__init__.py
StarkLego/lego_builders/service/builder.py
StarkLego/lego_builders/service/mapper.py
StarkLego/lego_builders/service/reader.py