Metadata-Version: 2.1
Name: StarkLego
Version: 0.1.7
Summary: Library used to create lego builds
Home-page: https://github.com/peken97/StarkLego
Author: Petar Kenic
Author-email: kenicpetar@yahoo.com
License: MIT
Keywords: LEGO,BUILD,LDRAW
Platform: UNKNOWN
Classifier: Development Status :: 3 - Alpha
Classifier: Intended Audience :: Developers
Classifier: Topic :: Software Development :: Build Tools
Classifier: License :: OSI Approved :: MIT License
Classifier: Programming Language :: Python :: 3.5
